bytestring_splitter/__about__.py
bytestring_splitter/__init__.py
bytestring_splitter-2.4.1.dist-info/LICENSE
bytestring_splitter-2.4.1.dist-info/METADATA
bytestring_splitter-2.4.1.dist-info/WHEEL
bytestring_splitter-2.4.1.dist-info/top_level.txt
bytestring_splitter-2.4.1.dist-info/RECORD
